calflops/__init__.py
calflops/calculate_pipline.py
calflops/estimate.py
calflops/flops_counter.py
calflops/flops_counter_hf.py
calflops/pytorch_ops.py
calflops/utils.py
calflops-0.3.1.dist-info/METADATA
calflops-0.3.1.dist-info/WHEEL
calflops-0.3.1.dist-info/licenses/LICENSE
calflops-0.3.1.dist-info/RECORD
