Metadata-Version: 2.3
Name: calflops
Version: 0.3.1
Summary: This package is designed to compute the theoretical amount of FLOPs(floating-point operations)、MACs(multiply-add operations) and Parameters in all various neural networks, such as Linear、 CNN、 RNN、 GCN、Transformer(Bert、LlaMA etc Large Language Model)，including any custom models via torch.nn.function.* as long as based on the Pytorch implementation.
Project-URL: Homepage, https://github.com/MrYxJ/calculate-flops.pytorch
Author-email: MrYXJ <yxj2017@gmail.com>
License: MIT License
License-File: LICENSE
Classifier: License :: OSI Approved :: MIT License
Classifier: Operating System :: OS Independent
Classifier: Programming Language :: Python :: 3
Requires-Python: >=3.6
Requires-Dist: accelerate>=0.22.0
Requires-Dist: huggingface-hub>=0.16.4
Requires-Dist: torch>=1.1.0
